websnort/__init__.py
websnort/config.py
websnort/plugins.py
websnort/runner.py
websnort/version.py
websnort/web.py
websnort/conf/websnort.conf
websnort/conf/websnort.conf.complex
websnort/conf/websnort.conf.suricata
websnort/conf/websnort.conf.windows
websnort/html/api.html
websnort/html/base.html
websnort/html/results.html
websnort/html/submit.html
websnort/html/css/bootstrap-responsive.min.css
websnort/html/css/bootstrap.min.css
websnort/html/img/glyphicons-halflings-white.png
websnort/html/img/glyphicons-halflings.png
websnort/html/js/bootstrap-filestyle.min.js
websnort/html/js/bootstrap.min.js
websnort/html/js/jquery.js
websnort/ids/__init__.py
websnort/ids/snort.py
websnort/ids/suricata.py
websnort-0.8.dist-info/METADATA
websnort-0.8.dist-info/RECORD
websnort-0.8.dist-info/WHEEL
websnort-0.8.dist-info/entry_points.txt
websnort-0.8.dist-info/top_level.txt
