Metadata-Version: 2.1
Name: websnort
Version: 0.8
Summary: Web service for analysing pcap files with snort
Home-page: https://github.com/shendo/websnort
Author: Steve Henderson
Author-email: steve.henderson@hendotech.com.au
License: GPL
Platform: UNKNOWN
Classifier: Development Status :: 4 - Beta
Classifier: Intended Audience :: Developers
Classifier: Intended Audience :: System Administrators
Classifier: License :: OSI Approved :: GNU General Public License v3 or later (GPLv3+)
Classifier: Operating System :: OS Independent
Classifier: Programming Language :: Python
Classifier: Programming Language :: Python :: 2
Classifier: Programming Language :: Python :: 2.7
Classifier: Programming Language :: Python :: 3
Classifier: Programming Language :: Python :: 3.4
Classifier: Programming Language :: Python :: 3.5
Classifier: Programming Language :: Python :: 3.6
Classifier: Programming Language :: Python :: 3.7
Classifier: Topic :: Internet
Classifier: Topic :: Security
Requires-Dist: bottle (>=0.10)
Requires-Dist: jinja2 (>=2.5)
